README.txt
setup.py
module_1/__init__.py
module_1/at_content.py
upload_dnatools_3.egg-info/PKG-INFO
upload_dnatools_3.egg-info/SOURCES.txt
upload_dnatools_3.egg-info/dependency_links.txt
upload_dnatools_3.egg-info/top_level.txt